furious/__init__.py
furious/cli/__init__.py
furious/cli/config.py
furious/cli/discover.py
furious/cli/exceptions.py
furious/cli/setup.py
furious/cli/bin/__init__.py
furious/cli/bin/furious.py
furious/cli/commands/run.py
furious/cli/commands/shell.py
furious_api-0.0.2.dist-info/METADATA
furious_api-0.0.2.dist-info/WHEEL
furious_api-0.0.2.dist-info/entry_points.txt
furious_api-0.0.2.dist-info/top_level.txt
furious_api-0.0.2.dist-info/RECORD
